pythonvideoannotator_module_eventsstats/__init__.py
pythonvideoannotator_module_eventsstats/module.py
pythonvideoannotator_module_eventsstats/stats.py
Python_video_annotator_module_eventstats-0.5.15.dist-info/METADATA
Python_video_annotator_module_eventstats-0.5.15.dist-info/WHEEL
Python_video_annotator_module_eventstats-0.5.15.dist-info/top_level.txt
Python_video_annotator_module_eventstats-0.5.15.dist-info/RECORD
